Metadata-Version: 2.1
Name: pysignals
Version: 0.1.4
Summary: Signal dispatcher for Python, extracted from the Django framework.
Home-page: https://github.com/theojulienne/PySignals
Author: Theo Julienne
Author-email: theo.julienne@gmail.com
License: UNKNOWN
Platform: any
License-File: LICENSE.txt
